[{"id":"Kiev1646936010808","city":"Kiev","description":"Fire Safety","inspector":"Simon Schlatt","notes":[{"issue":"whatever","recomendations":"dont know","photo":"1647364046966-tree.jpg"}]},{"id":"Lviv1646936025833","city":"Lviv","description":"Carcass rot","inspector":"Oleg Khmara","notes":[{"issue":"awet","recomendations":"awer","photo":"1647364315874-house.jpg"},{"issue":"qw4t","recomendations":"3q4t","photo":"1647364354164-road.jpg"}]},{"id":"Kharkiv1646936049807","city":"Kharkiv","description":"Water supply","inspector":"Jarred Olaf","notes":[{"issue":"Dirty floor","recomendations":"Sweep the floor","photo":"1647102997205-floor.jpeg"},{"issue":"Lack of electricity ","recomendations":"Increase the supply or reconsider electricity options","photo":"1647110955281-dark.jpg"},{"issue":"Rust on south of store","recomendations":"Use anticorrosion solutions","photo":"1647111498636-rust.jpg"}]},{"id":"Poltava1647021103284","city":"Poltava","description":"Gas issues","inspector":"Oleg Khmara","notes":[]}]